eiswarnung/__init__.py
eiswarnung/eiswarnung.py
eiswarnung/exceptions.py
eiswarnung/models.py
eiswarnung/py.typed
eiswarnung-2.0.0.dist-info/LICENSE
eiswarnung-2.0.0.dist-info/METADATA
eiswarnung-2.0.0.dist-info/WHEEL
eiswarnung-2.0.0.dist-info/RECORD
